boat_torch/__init__.py
boat_torch/boat_opt.py
boat_torch/operation_registry.py
boat_torch/dynamic_ol/__init__.py
boat_torch/dynamic_ol/di.py
boat_torch/dynamic_ol/dm.py
boat_torch/dynamic_ol/dynamical_system.py
boat_torch/dynamic_ol/gda.py
boat_torch/dynamic_ol/ngd.py
boat_torch/dynamic_ol/sequential_ds.py
boat_torch/fogm/__init__.py
boat_torch/fogm/mesm.py
boat_torch/fogm/pgdm.py
boat_torch/fogm/vfm.py
boat_torch/fogm/vsm.py
boat_torch/hyper_ol/__init__.py
boat_torch/hyper_ol/cg.py
boat_torch/hyper_ol/fd.py
boat_torch/hyper_ol/foa.py
boat_torch/hyper_ol/hyper_gradient.py
boat_torch/hyper_ol/iad.py
boat_torch/hyper_ol/iga.py
boat_torch/hyper_ol/ns.py
boat_torch/hyper_ol/ptt.py
boat_torch/hyper_ol/rad.py
boat_torch/hyper_ol/rgt.py
boat_torch/hyper_ol/sequential_hg.py
boat_torch/utils/__init__.py
boat_torch/utils/op_utils.py
boat_torch-1.0.1.dist-info/LICENSE
boat_torch-1.0.1.dist-info/METADATA
boat_torch-1.0.1.dist-info/WHEEL
boat_torch-1.0.1.dist-info/top_level.txt
boat_torch-1.0.1.dist-info/RECORD
