Metadata-Version: 2.1
Name: boat-torch
Version: 1.0.1
Summary: Problem-Agnostic Bilevel Optimization Toolkit in Python for Learning and Vision Tasks
Home-page: https://github.com/callous-youth/BOAT
Author: Yaohua Liu, Xianghao Jiao, Risheng Liu
Author-email: liuyaohua.918@gmail.com
License: MIT
Keywords: Bilevel-optimization,Learning and vision,Python,Deep learning,PyTorch
Classifier: License :: OSI Approved :: MIT License
Classifier: Programming Language :: Python :: 3
Classifier: Programming Language :: Python :: 3.8
Classifier: Operating System :: OS Independent
Requires-Python: >=3.8.0
License-File: LICENSE
Requires-Dist: numpy
Requires-Dist: setuptools
Requires-Dist: torch>=1.4
Requires-Dist: higher
Requires-Dist: matplotlib
